rsa_bootrom_tool-0.2.3.dist-info/licenses/LICENSE
rsa_tool/__init__.py
rsa_tool/cli.py
rsa_bootrom_tool-0.2.3.dist-info/METADATA
rsa_bootrom_tool-0.2.3.dist-info/WHEEL
rsa_bootrom_tool-0.2.3.dist-info/entry_points.txt
rsa_bootrom_tool-0.2.3.dist-info/top_level.txt
rsa_bootrom_tool-0.2.3.dist-info/RECORD
