Metadata-Version: 2.4
Name: rsa-bootrom-tool
Version: 0.2.3
Summary: RSA Tool for BootROM secure boot keygen/sign/verify/export
Author-email: Your Name <you@example.com>
License-Expression: MIT
Requires-Python: >=3.6
License-File: LICENSE
Requires-Dist: pycryptodome
Dynamic: license-file
